{
  "pos": {
    "version": "1.5.13",
    "is_mandatory": false,
    "download_url": "https://github.com/muhivan752/Kasira-OS-Intelligence/releases/download/v1.5.13/kasira-pos-v1.5.13.apk",
    "release_notes": "Stok simple mode sinkron dashboard-HP (server-authoritative)."
  },
  "dapur": {
    "version": "1.5.13",
    "is_mandatory": false,
    "download_url": "https://github.com/muhivan752/Kasira-OS-Intelligence/releases/download/v1.5.13/kasira-dapur-v1.5.13.apk",
    "release_notes": "Stok simple mode sinkron dashboard-HP (server-authoritative)."
  }
}
